set_detect_notify/__init__.py
set_detect_notify/__main__.py
set_detect_notify/utils/__init__.py
set_detect_notify/utils/notify.py
set_detect_notify/utils/utils.py
set_detect_notify-0.1.0.dist-info/entry_points.txt
set_detect_notify-0.1.0.dist-info/LICENSE
set_detect_notify-0.1.0.dist-info/METADATA
set_detect_notify-0.1.0.dist-info/WHEEL
set_detect_notify-0.1.0.dist-info/RECORD
