Metadata-Version: 2.1
Name: set-detect-notify
Version: 0.1.0
Summary: Detect all the things
License: MIT
Author: slashtechno
Author-email: 77907286+slashtechno@users.noreply.github.com
Requires-Python: >=3.10,<3.12
Classifier: License :: OSI Approved :: MIT License
Classifier: Programming Language :: Python :: 3
Classifier: Programming Language :: Python :: 3.10
Classifier: Programming Language :: Python :: 3.11
Requires-Dist: deepface (>=0.0.79,<0.0.80)
Requires-Dist: hjson (>=3.1.0,<4.0.0)
Requires-Dist: httpx (>=0.25.0,<0.26.0)
Requires-Dist: numpy (>=1.23.2,<2.0.0)
Requires-Dist: opencv-python (>=4.8.1.78,<5.0.0.0)
Requires-Dist: python-dotenv (>=1.0.0,<2.0.0)
Requires-Dist: tensorflow-io-gcs-filesystem (==0.31.0)
Requires-Dist: torch (>=2.0.0,!=2.0.1,!=2.1.0)
Requires-Dist: ultralytics (>=8.0.190,<9.0.0)
